{
	"name": "Pivot_Transformation6",
	"properties": {
		"type": "MappingDataFlow",
		"typeProperties": {
			"sources": [
				{
					"dataset": {
						"referenceName": "Pivot_Transformation6_Source",
						"type": "DatasetReference"
					},
					"name": "source1"
				}
			],
			"sinks": [
				{
					"dataset": {
						"referenceName": "Pivot_Transformation6_Destination",
						"type": "DatasetReference"
					},
					"name": "sink1"
				}
			],
			"transformations": [
				{
					"name": "pivot1"
				},
				{
					"name": "surrogateKey1"
				}
			],
			"scriptLines": [
				"source(output(",
				"          stockId as short,",
				"          item as string,",
				"          Quantity as short,",
				"          year as short",
				"     ),",
				"     allowSchemaDrift: true,",
				"     validateSchema: false,",
				"     ignoreNoFilesFound: false) ~> source1",
				"source1 pivot(groupBy(item),",
				"     pivotBy(year),",
				"     {} = sum(Quantity),",
				"     columnNaming: '$N$V',",
				"     lateral: true) ~> pivot1",
				"pivot1 keyGenerate(output({S.No} as long),",
				"     startAt: 1L,",
				"     stepValue: 1L) ~> surrogateKey1",
				"surrogateKey1 sink(allowSchemaDrift: true,",
				"     validateSchema: false,",
				"     partitionFileNames:['Pivot_Output'],",
				"     umask: 0022,",
				"     preCommands: [],",
				"     postCommands: [],",
				"     skipDuplicateMapInputs: true,",
				"     skipDuplicateMapOutputs: true,",
				"     partitionBy('hash', 1)) ~> sink1"
			]
		}
	}
}